istao/__init__.py
istao/istao.py
istao-0.4.dist-info/LICENSE
istao-0.4.dist-info/METADATA
istao-0.4.dist-info/WHEEL
istao-0.4.dist-info/top_level.txt
istao-0.4.dist-info/RECORD
