Metadata-Version: 2.1
Name: istao
Version: 0.4
Summary: Library for Tao Python applications to check if the intended operating system is being used
Home-page: https://github.com/Tao-Linux/python-istao
Author: Yatoub
Project-URL: Bug Tracker, https://github.com/Tao-Linux/python-istao/issues
Classifier: Programming Language :: Python :: 3
Classifier: License :: OSI Approved :: GNU General Public License v3 (GPLv3)
Classifier: Operating System :: OS Independent
License-File: LICENSE
Requires-Dist: distro
Requires-Dist: colorama
